decorate/__init__.py
decorate/__main__.py
decorate/themes/basic/basic.css
decorate/themes/basic/basic.js
decorate/themes/basic/spec.yaml
decorate/themes/bootstrap/spec.yaml
decorate/themes/mdl/spec.yaml
decorate-1.0.0.dist-info/DESCRIPTION.rst
decorate-1.0.0.dist-info/METADATA
decorate-1.0.0.dist-info/RECORD
decorate-1.0.0.dist-info/WHEEL
decorate-1.0.0.dist-info/entry_points.txt
decorate-1.0.0.dist-info/metadata.json
decorate-1.0.0.dist-info/top_level.txt
