Metadata-Version: 2.0
Name: decorate
Version: 1.0.0
Summary: Decorate HTML docs by adding them classes by theme
Home-page: https://github.com/magmax/decorate
Author: Miguel Ángel García
Author-email: miguelangel.garcia@gmail.com
License: MIT
Keywords: HTML class bootstrap material design
Platform: UNKNOWN
Classifier: Development Status :: 1 - Planning
Classifier: Programming Language :: Python :: 2.7
Classifier: Programming Language :: Python :: 3.3
Classifier: Programming Language :: Python :: 3.4
Classifier: Programming Language :: Python :: 3.5
Classifier: Programming Language :: Python :: Implementation :: CPython
Classifier: Programming Language :: Python :: Implementation :: PyPy
Classifier: License :: OSI Approved :: MIT License
Classifier: Topic :: Software Development :: Code Generators
Classifier: Topic :: Text Processing :: Markup :: HTML
Classifier: Operating System :: OS Independent
Requires-Dist: cssselect (>=0.9.1)
Requires-Dist: lxml (>=3.6.0)
Provides-Extra: develop
Requires-Dist: coveralls (>=1.1); extra == 'develop'
Requires-Dist: flake8 (>=2.5.4); extra == 'develop'
Requires-Dist: pytest (>=2.6.4); extra == 'develop'
Requires-Dist: pytest-cov (>=2.2.1); extra == 'develop'
Provides-Extra: yaml
Requires-Dist: pyyaml (>=3.11); extra == 'yaml'
